odoo/addons/account_avatax_sale/README.rst
odoo/addons/account_avatax_sale/__init__.py
odoo/addons/account_avatax_sale/__manifest__.py
odoo/addons/account_avatax_sale/i18n/account_avatax_sale.pot
odoo/addons/account_avatax_sale/models/__init__.py
odoo/addons/account_avatax_sale/models/account_move.py
odoo/addons/account_avatax_sale/models/account_tax.py
odoo/addons/account_avatax_sale/models/avalara_salestax.py
odoo/addons/account_avatax_sale/models/partner.py
odoo/addons/account_avatax_sale/models/sale_order.py
odoo/addons/account_avatax_sale/readme/CONTRIBUTORS.rst
odoo/addons/account_avatax_sale/readme/DESCRIPTION.rst
odoo/addons/account_avatax_sale/readme/USAGE.rst
odoo/addons/account_avatax_sale/static/description/icon.png
odoo/addons/account_avatax_sale/static/description/index.html
odoo/addons/account_avatax_sale/views/avalara_salestax_view.xml
odoo/addons/account_avatax_sale/views/partner_view.xml
odoo/addons/account_avatax_sale/views/sale_order_view.xml
odoo_addon_account_avatax_sale-15.0.1.1.0.dist-info/METADATA
odoo_addon_account_avatax_sale-15.0.1.1.0.dist-info/WHEEL
odoo_addon_account_avatax_sale-15.0.1.1.0.dist-info/top_level.txt
odoo_addon_account_avatax_sale-15.0.1.1.0.dist-info/RECORD
